{
  "name": "Header",
  "type": "header",
  "sections": {
    "header": {
      "type": "header",
      "blocks": {
        "df8faed4-da3f-4f2f-9346-6de89de4e116": {
          "type": "mega_menu",
          "settings": {
            "mega_menu_index": 4,
            "mega_menu_card_1_text": "Individual Products",
            "mega_menu_card_1_link": "shopify:\/\/products\/collagen",
            "mega_menu_card_1_target": "_self",
            "mega_menu_card_2_text": "Systems",
            "mega_menu_card_2_link": "shopify:\/\/products\/the-collagen-c-bundle-1",
            "mega_menu_card_2_target": "_self"
          }
        }
      },
      "block_order": [
        "df8faed4-da3f-4f2f-9346-6de89de4e116"
      ],
      "settings": {
        "fullwidth": true,
        "width": 2000,
        "color_scheme": "scheme-main",
        "inset": true,
        "inset_choice": "level-2",
        "logo": "shopify:\/\/shop_images\/primary_logo_GReen.png",
        "logo_height": 52,
        "primary_menu": "header-menu",
        "cart_icon": false,
        "search_icon": false,
        "search_dropdown_offset": 70,
        "country_selector": true,
        "language_selector": false,
        "primary_menu_collection_image_display": false,
        "primary_menu_sticky": true,
        "separator": false,
        "separator_height": 1,
        "separator_use_custom_color": false,
        "separator_custom_color": "#dad3c4"
      }
    },
    "announcement-bar": {
      "type": "announcement-bar",
      "blocks": {
        "announcement-bar-0": {
          "type": "announcement",
          "settings": {
            "text": "Become A Member for Supplements Delivered Straight To Your Door - Every Other Month",
            "btn_text": "",
            "btn_url": "",
            "btn_target": "_self"
          }
        }
      },
      "block_order": [
        "announcement-bar-0"
      ],
      "settings": {
        "fullwidth": true,
        "width": 1320,
        "color_scheme": "scheme-main",
        "inset": false,
        "inset_choice": "level-2",
        "outline": true,
        "carousel": true,
        "autoplay": true,
        "interval": 4000,
        "loop": true,
        "mouse_drag": true,
        "arrows": true,
        "dots": false,
        "speed": 400
      }
    }
  },
  "order": [
    "header",
    "announcement-bar"
  ]
}
